gitlab_multi_group_runner/__init__.py
gitlab_multi_group_runner/_version.py
gitlab_multi_group_runner/cli.py
gitlab_multi_group_runner/config.py
gitlab_multi_group_runner/gitlab.py
gitlab_multi_group_runner/utils.py
gitlab_multi_group_runner-0.1.2.dist-info/LICENSE
gitlab_multi_group_runner-0.1.2.dist-info/METADATA
gitlab_multi_group_runner-0.1.2.dist-info/WHEEL
gitlab_multi_group_runner-0.1.2.dist-info/entry_points.txt
gitlab_multi_group_runner-0.1.2.dist-info/top_level.txt
gitlab_multi_group_runner-0.1.2.dist-info/RECORD
