Metadata-Version: 2.1
Name: gitlab-multi-group-runner
Version: 0.1.2
Summary: A helper to assign a GitLab runner to multiple groups and projects
Home-page: https://github.com/sciapp/gitlab-multi-group-runner
Author: Ingo Meyer
Author-email: i.meyer@fz-juelich.de
License: MIT
Keywords: gitlab,ci,runner,multi-group
Platform: UNKNOWN
Classifier: Development Status :: 4 - Beta
Classifier: Environment :: Console
Classifier: Intended Audience :: Developers
Classifier: Intended Audience :: System Administrators
Classifier: License :: OSI Approved :: MIT License
Classifier: Operating System :: POSIX :: Linux
Classifier: Programming Language :: Python
Classifier: Programming Language :: Python :: 3
Classifier: Programming Language :: Python :: 3.6
Classifier: Programming Language :: Python :: 3.7
Classifier: Programming Language :: Python :: 3.8
Classifier: Programming Language :: Python :: 3.9
Classifier: Programming Language :: Python :: 3.10
Classifier: Programming Language :: Python :: 3 :: Only
Classifier: Topic :: Software Development
Classifier: Topic :: Software Development :: Version Control
Classifier: Topic :: Software Development :: Version Control :: Git
Classifier: Topic :: Utilities
Requires-Python: ~=3.6
License-File: LICENSE
Requires-Dist: cerberus
Requires-Dist: python-gitlab
Requires-Dist: pyyaml
Requires-Dist: yacl[colored_exceptions]
